{"i.instagram.com":{"/":{"ds_user":{"key":"ds_user","value":"it_koverko","expires":"2020-02-15T16:07:27.000Z","maxAge":7776000,"domain":"i.instagram.com","path":"/","secure":true,"httpOnly":true,"hostOnly":true,"creation":"2019-11-17T16:07:28.137Z","lastAccessed":"2019-11-17T16:14:24.313Z"},"csrftoken":{"key":"csrftoken","value":"6z5z0A6uUivHe5mEARYanBuWY84WSike","expires":"2020-11-15T16:14:24.000Z","maxAge":31449600,"domain":"i.instagram.com","path":"/","secure":true,"hostOnly":true,"creation":"2019-11-17T16:07:28.139Z","lastAccessed":"2019-11-17T16:14:24.754Z"},"rur":{"key":"rur","value":"FTW","domain":"i.instagram.com","path":"/","secure":true,"httpOnly":true,"hostOnly":true,"creation":"2019-11-17T16:07:28.140Z","lastAccessed":"2019-11-17T16:14:24.759Z"},"mid":{"key":"mid","value":"XdFwPgABAAG1jX7Ii-j4wfWAdoU-","expires":"2029-11-14T16:07:27.000Z","maxAge":315360000,"domain":"i.instagram.com","path":"/","secure":true,"hostOnly":true,"creation":"2019-11-17T16:07:28.140Z","lastAccessed":"2019-11-17T16:14:24.313Z"},"ds_user_id":{"key":"ds_user_id","value":"24189697725","expires":"2020-02-15T16:07:28.000Z","maxAge":7776000,"domain":"i.instagram.com","path":"/","secure":true,"hostOnly":true,"creation":"2019-11-17T16:07:28.140Z","lastAccessed":"2019-11-17T16:14:24.313Z"},"sessionid":{"key":"sessionid","value":"24189697725%3ADYJum1eMsUM8x5%3A22","expires":"2020-11-16T16:07:27.000Z","maxAge":31536000,"domain":"i.instagram.com","path":"/","secure":true,"httpOnly":true,"hostOnly":true,"creation":"2019-11-17T16:07:28.141Z","lastAccessed":"2019-11-17T16:14:24.313Z"},"urlgen":{"key":"urlgen","value":"\"{\\\"46.216.144.135\\\": 25106}:1iWNBw:uUR1pEMA97mcFYVW0_SoV8pNeD0\"","domain":"i.instagram.com","path":"/","secure":true,"httpOnly":true,"hostOnly":true,"creation":"2019-11-17T16:07:29.660Z","lastAccessed":"2019-11-17T16:14:24.760Z"}}}}